{"name":"ITSM","created":"2018-01-24T22:01:23.119Z","intents":[{"intent":"greetings","created":"2018-01-24T22:12:06.764Z","updated":"2018-01-24T22:12:06.764Z","examples":[{"text":"yo my man","created":"2018-01-24T22:12:06.764Z","updated":"2018-01-24T22:12:06.764Z"},{"text":"yo","created":"2018-01-24T22:12:06.764Z","updated":"2018-01-24T22:12:06.764Z"},{"text":"yello","created":"2018-01-24T22:12:06.764Z","updated":"2018-01-24T22:12:06.764Z"},{"text":"What's up?","created":"2018-01-24T22:12:06.764Z","updated":"2018-01-24T22:12:06.764Z"},{"text":"What's up ?","created":"2018-01-24T22:12:06.764Z","updated":"2018-01-24T22:12:06.764Z"},{"text":"What's up","created":"2018-01-24T22:12:06.764Z","updated":"2018-01-24T22:12:06.764Z"},{"text":"what r u doing","created":"2018-01-24T22:12:06.764Z","updated":"2018-01-24T22:12:06.764Z"},{"text":"what doing","created":"2018-01-24T22:12:06.764Z","updated":"2018-01-24T22:12:06.764Z"},{"text":"sup","created":"2018-01-24T22:12:06.764Z","updated":"2018-01-24T22:12:06.764Z"},{"text":"say hello to me","created":"2018-01-24T22:12:06.764Z","updated":"2018-01-24T22:12:06.764Z"},{"text":"namaste","created":"2018-01-24T22:12:06.764Z","updated":"2018-01-24T22:12:06.764Z"},{"text":"I would like you to say hello","created":"2018-01-24T22:12:06.764Z","updated":"2018-01-24T22:12:06.764Z"},{"text":"howdy","created":"2018-01-24T22:12:06.764Z","updated":"2018-01-24T22:12:06.764Z"},{"text":"How are you doing","created":"2018-01-24T22:12:06.764Z","updated":"2018-01-24T22:12:06.764Z"},{"text":"hola como estas","created":"2018-01-24T22:12:06.764Z","updated":"2018-01-24T22:12:06.764Z"},{"text":"Hola","created":"2018-01-24T22:12:06.764Z","updated":"2018-01-24T22:12:06.764Z"},{"text":"hiya","created":"2018-01-24T22:12:06.764Z","updated":"2018-01-24T22:12:06.764Z"},{"text":"Hi, Watson, my name is John","created":"2018-01-24T22:12:06.764Z","updated":"2018-01-24T22:12:06.764Z"},{"text":"Hi watson","created":"2018-01-24T22:12:06.764Z","updated":"2018-01-24T22:12:06.764Z"},{"text":"hi to whom had like","created":"2018-01-24T22:12:06.764Z","updated":"2018-01-24T22:12:06.764Z"},{"text":"hi there","created":"2018-01-24T22:12:06.764Z","updated":"2018-01-24T22:12:06.764Z"},{"text":"Hi, my name is Michel","created":"2018-01-24T22:12:06.764Z","updated":"2018-01-24T22:12:06.764Z"},{"text":"Hi, my name is Diego","created":"2018-01-24T22:12:06.764Z","updated":"2018-01-24T22:12:06.764Z"},{"text":"hi how are u","created":"2018-01-24T22:12:06.764Z","updated":"2018-01-24T22:12:06.764Z"},{"text":"hi","created":"2018-01-24T22:12:06.764Z","updated":"2018-01-24T22:12:06.764Z"},{"text":"hey there","created":"2018-01-24T22:12:06.764Z","updated":"2018-01-24T22:12:06.764Z"},{"text":"heya","created":"2018-01-24T22:12:06.764Z","updated":"2018-01-24T22:12:06.764Z"},{"text":"hey","created":"2018-01-24T22:12:06.764Z","updated":"2018-01-24T22:12:06.764Z"},{"text":"Hello Watson","created":"2018-01-24T22:12:06.764Z","updated":"2018-01-24T22:12:06.764Z"},{"text":"Hello, My name is John?","created":"2018-01-24T22:12:06.764Z","updated":"2018-01-24T22:12:06.764Z"},{"text":"hello, my name is esteban","created":"2018-01-24T22:12:06.764Z","updated":"2018-01-24T22:12:06.764Z"},{"text":"Hello, how are you","created":"2018-01-24T22:12:06.764Z","updated":"2018-01-24T22:12:06.764Z"},{"text":"Hello","created":"2018-01-24T22:12:06.764Z","updated":"2018-01-24T22:12:06.764Z"},{"text":"greetings","created":"2018-01-24T22:12:06.764Z","updated":"2018-01-24T22:12:06.764Z"},{"text":"good morning","created":"2018-01-24T22:12:06.764Z","updated":"2018-01-24T22:12:06.764Z"},{"text":"good how are you","created":"2018-01-24T22:12:06.764Z","updated":"2018-01-24T22:12:06.764Z"},{"text":"good evening","created":"2018-01-24T22:12:06.764Z","updated":"2018-01-24T22:12:06.764Z"},{"text":"good day","created":"2018-01-24T22:12:06.764Z","updated":"2018-01-24T22:12:06.764Z"},{"text":"Good afternoon.","created":"2018-01-24T22:12:06.764Z","updated":"2018-01-24T22:12:06.764Z"},{"text":"good","created":"2018-01-24T22:12:06.764Z","updated":"2018-01-24T22:12:06.764Z"},{"text":"g'day","created":"2018-01-24T22:12:06.764Z","updated":"2018-01-24T22:12:06.764Z"},{"text":"feeling bit low","created":"2018-01-24T22:12:06.764Z","updated":"2018-01-24T22:12:06.764Z"},{"text":"fdsafsaHi watson","created":"2018-01-24T22:12:06.764Z","updated":"2018-01-24T22:12:06.764Z"},{"text":"ciao","created":"2018-01-24T22:12:06.764Z","updated":"2018-01-24T22:12:06.764Z"},{"text":"buenos dias","created":"2018-01-24T22:12:06.764Z","updated":"2018-01-24T22:12:06.764Z"},{"text":"buenas dias","created":"2018-01-24T22:12:06.764Z","updated":"2018-01-24T22:12:06.764Z"},{"text":"bonjour","created":"2018-01-24T22:12:06.764Z","updated":"2018-01-24T22:12:06.764Z"},{"text":"aloha","created":"2018-01-24T22:12:06.764Z","updated":"2018-01-24T22:12:06.764Z"}],"description":null},{"intent":"IT_helpdesk","created":"2018-01-24T22:12:06.764Z","updated":"2018-01-25T03:04:25.971Z","examples":[{"text":"My computer is not working","created":"2018-01-24T22:12:06.764Z","updated":"2018-01-24T22:12:06.764Z"},{"text":"My computer does not work","created":"2018-01-24T22:12:06.764Z","updated":"2018-01-24T22:12:06.764Z"},{"text":"My computer has problem","created":"2018-01-24T22:12:06.764Z","updated":"2018-01-24T22:12:06.764Z"},{"text":"My computer has issue","created":"2018-01-24T22:12:06.764Z","updated":"2018-01-24T22:12:06.764Z"},{"text":"can't login to HR application","created":"2018-01-24T22:12:06.764Z","updated":"2018-01-24T22:12:06.764Z"},{"text":"Can't access portal server","created":"2018-01-24T22:12:06.764Z","updated":"2018-01-24T22:12:06.764Z"},{"text":"Network is down","created":"2018-01-24T22:12:06.764Z","updated":"2018-01-24T22:12:06.764Z"},{"text":"Network is slow","created":"2018-01-24T22:12:06.764Z","updated":"2018-01-24T22:12:06.764Z"},{"text":"need wireless password","created":"2018-01-24T22:12:06.764Z","updated":"2018-01-24T22:12:06.764Z"},{"text":"database is down","created":"2018-01-25T03:04:01.215Z","updated":"2018-01-25T03:04:01.215Z"},{"text":"can't connect to database","created":"2018-01-25T03:04:12.477Z","updated":"2018-01-25T03:04:12.477Z"},{"text":"can't connect to db2","created":"2018-01-25T03:04:18.527Z","updated":"2018-01-25T03:04:18.527Z"},{"text":"db2 is down","created":"2018-01-25T03:04:25.971Z","updated":"2018-01-25T03:04:25.971Z"}],"description":null},{"intent":"ticketing","created":"2018-01-24T22:12:54.717Z","updated":"2018-01-24T22:14:08.645Z","examples":[{"text":"create new sr","created":"2018-01-24T22:13:03.533Z","updated":"2018-01-24T22:13:03.533Z"},{"text":"create sr","created":"2018-01-24T22:13:07.759Z","updated":"2018-01-24T22:13:07.759Z"},{"text":"create ticket","created":"2018-01-24T22:13:13.790Z","updated":"2018-01-24T22:13:13.790Z"},{"text":"create new ticket","created":"2018-01-24T22:13:44.751Z","updated":"2018-01-24T22:13:44.751Z"},{"text":"open ticket","created":"2018-01-24T22:13:48.624Z","updated":"2018-01-24T22:13:48.624Z"},{"text":"open new ticket","created":"2018-01-24T22:13:54.160Z","updated":"2018-01-24T22:13:54.160Z"},{"text":"report problem","created":"2018-01-24T22:14:03.571Z","updated":"2018-01-24T22:14:03.571Z"},{"text":"report new problem","created":"2018-01-24T22:14:08.645Z","updated":"2018-01-24T22:14:08.645Z"}],"description":"create new ticket"},{"intent":"goodbyes","created":"2018-01-24T22:12:06.764Z","updated":"2018-01-24T22:12:06.764Z","examples":[{"text":"toodles","created":"2018-01-24T22:12:06.764Z","updated":"2018-01-24T22:12:06.764Z"},{"text":"then bye","created":"2018-01-24T22:12:06.764Z","updated":"2018-01-24T22:12:06.764Z"},{"text":"thanks byebye","created":"2018-01-24T22:12:06.764Z","updated":"2018-01-24T22:12:06.764Z"},{"text":"swag out","created":"2018-01-24T22:12:06.764Z","updated":"2018-01-24T22:12:06.764Z"},{"text":"soon","created":"2018-01-24T22:12:06.764Z","updated":"2018-01-24T22:12:06.764Z"},{"text":"so long","created":"2018-01-24T22:12:06.764Z","updated":"2018-01-24T22:12:06.764Z"},{"text":"signing out","created":"2018-01-24T22:12:06.764Z","updated":"2018-01-24T22:12:06.764Z"},{"text":"signing off","created":"2018-01-24T22:12:06.764Z","updated":"2018-01-24T22:12:06.764Z"},{"text":"shut down","created":"2018-01-24T22:12:06.764Z","updated":"2018-01-24T22:12:06.764Z"},{"text":"shutdown","created":"2018-01-24T22:12:06.764Z","updated":"2018-01-24T22:12:06.764Z"},{"text":"should go","created":"2018-01-24T22:12:06.764Z","updated":"2018-01-24T22:12:06.764Z"},{"text":"should be going","created":"2018-01-24T22:12:06.764Z","updated":"2018-01-24T22:12:06.764Z"},{"text":"see you","created":"2018-01-24T22:12:06.764Z","updated":"2018-01-24T22:12:06.764Z"},{"text":"see ya soon","created":"2018-01-24T22:12:06.764Z","updated":"2018-01-24T22:12:06.764Z"},{"text":"see ya later","created":"2018-01-24T22:12:06.764Z","updated":"2018-01-24T22:12:06.764Z"},{"text":"see ya","created":"2018-01-24T22:12:06.764Z","updated":"2018-01-24T22:12:06.764Z"},{"text":"run","created":"2018-01-24T22:12:06.764Z","updated":"2018-01-24T22:12:06.764Z"},{"text":"over and out","created":"2018-01-24T22:12:06.764Z","updated":"2018-01-24T22:12:06.764Z"},{"text":"out of time","created":"2018-01-24T22:12:06.764Z","updated":"2018-01-24T22:12:06.764Z"},{"text":"ok bye","created":"2018-01-24T22:12:06.764Z","updated":"2018-01-24T22:12:06.764Z"},{"text":"no, bye!","created":"2018-01-24T22:12:06.764Z","updated":"2018-01-24T22:12:06.764Z"},{"text":"nice day","created":"2018-01-24T22:12:06.764Z","updated":"2018-01-24T22:12:06.764Z"},{"text":"my time is up","created":"2018-01-24T22:12:06.764Z","updated":"2018-01-24T22:12:06.764Z"},{"text":"logging off","created":"2018-01-24T22:12:06.764Z","updated":"2018-01-24T22:12:06.764Z"},{"text":"leave","created":"2018-01-24T22:12:06.764Z","updated":"2018-01-24T22:12:06.764Z"},{"text":"laters","created":"2018-01-24T22:12:06.764Z","updated":"2018-01-24T22:12:06.764Z"},{"text":"later","created":"2018-01-24T22:12:06.764Z","updated":"2018-01-24T22:12:06.764Z"},{"text":"i said goodbye","created":"2018-01-24T22:12:06.764Z","updated":"2018-01-24T22:12:06.764Z"},{"text":"I'm leaving","created":"2018-01-24T22:12:06.764Z","updated":"2018-01-24T22:12:06.764Z"},{"text":"Hi, Watson. I want to stop car","created":"2018-01-24T22:12:06.764Z","updated":"2018-01-24T22:12:06.764Z"},{"text":"hey stop here","created":"2018-01-24T22:12:06.764Z","updated":"2018-01-24T22:12:06.764Z"},{"text":"Have a nice day","created":"2018-01-24T22:12:06.764Z","updated":"2018-01-24T22:12:06.764Z"},{"text":"gtg","created":"2018-01-24T22:12:06.764Z","updated":"2018-01-24T22:12:06.764Z"},{"text":"gotta run","created":"2018-01-24T22:12:06.764Z","updated":"2018-01-24T22:12:06.764Z"},{"text":"gotta go","created":"2018-01-24T22:12:06.764Z","updated":"2018-01-24T22:12:06.764Z"},{"text":"good night","created":"2018-01-24T22:12:06.764Z","updated":"2018-01-24T22:12:06.764Z"},{"text":"good day","created":"2018-01-24T22:12:06.764Z","updated":"2018-01-24T22:12:06.764Z"},{"text":"good bye","created":"2018-01-24T22:12:06.764Z","updated":"2018-01-24T22:12:06.764Z"},{"text":"goodbye","created":"2018-01-24T22:12:06.764Z","updated":"2018-01-24T22:12:06.764Z"},{"text":"going","created":"2018-01-24T22:12:06.764Z","updated":"2018-01-24T22:12:06.764Z"},{"text":"go","created":"2018-01-24T22:12:06.764Z","updated":"2018-01-24T22:12:06.764Z"},{"text":"finally reached home.. lock up and cock up.. good nite and good bye for ever","created":"2018-01-24T22:12:06.764Z","updated":"2018-01-24T22:12:06.764Z"},{"text":"farewell","created":"2018-01-24T22:12:06.764Z","updated":"2018-01-24T22:12:06.764Z"},{"text":"cya","created":"2018-01-24T22:12:06.764Z","updated":"2018-01-24T22:12:06.764Z"},{"text":"bye now","created":"2018-01-24T22:12:06.764Z","updated":"2018-01-24T22:12:06.764Z"},{"text":"bye bye","created":"2018-01-24T22:12:06.764Z","updated":"2018-01-24T22:12:06.764Z"},{"text":"bye","created":"2018-01-24T22:12:06.764Z","updated":"2018-01-24T22:12:06.764Z"},{"text":"au revoir","created":"2018-01-24T22:12:06.764Z","updated":"2018-01-24T22:12:06.764Z"},{"text":"adios","created":"2018-01-24T22:12:06.764Z","updated":"2018-01-24T22:12:06.764Z"},{"text":"adieu","created":"2018-01-24T22:12:06.764Z","updated":"2018-01-24T22:12:06.764Z"}],"description":null},{"intent":"answer","created":"2018-01-26T20:38:47.462Z","updated":"2018-01-26T20:39:53.841Z","examples":[{"text":"yes","created":"2018-01-26T20:39:09.417Z","updated":"2018-01-26T20:39:09.417Z"},{"text":"y","created":"2018-01-26T20:39:11.704Z","updated":"2018-01-26T20:39:11.704Z"},{"text":"true","created":"2018-01-26T20:39:25.637Z","updated":"2018-01-26T20:39:25.637Z"},{"text":"false","created":"2018-01-26T20:39:31.772Z","updated":"2018-01-26T20:39:31.772Z"},{"text":"no","created":"2018-01-26T20:39:34.145Z","updated":"2018-01-26T20:39:34.145Z"},{"text":"not","created":"2018-01-26T20:39:36.797Z","updated":"2018-01-26T20:39:36.797Z"},{"text":"f","created":"2018-01-26T20:39:48.477Z","updated":"2018-01-26T20:39:48.477Z"},{"text":"n","created":"2018-01-26T20:39:53.841Z","updated":"2018-01-26T20:39:53.841Z"}],"description":""}],"updated":"2018-01-27T06:20:36.794Z","entities":[{"entity":"sys-number","values":[],"created":"2018-01-24T22:01:23.119Z","updated":"2018-01-24T22:01:23.119Z","metadata":null,"description":null},{"entity":"new_ticket","values":[{"type":"synonyms","value":"true","created":"2018-01-25T03:23:04.656Z","updated":"2018-01-25T03:41:26.750Z","metadata":null,"synonyms":["true","yes","yeah","y","t"]},{"type":"synonyms","value":"no","created":"2018-01-25T03:23:29.257Z","updated":"2018-01-26T20:45:41.227Z","metadata":null,"synonyms":["false","no","not","n","f"]}],"created":"2018-01-25T03:22:36.124Z","updated":"2018-01-26T20:45:41.227Z","metadata":null,"description":null},{"entity":"Hardware","values":[{"type":"synonyms","value":"Printer","created":"2018-01-24T22:01:23.119Z","updated":"2018-01-24T22:01:23.119Z","metadata":null,"synonyms":["Laser printer","Line printer","Ink printer"]},{"type":"synonyms","value":"Computer","created":"2018-01-24T22:01:23.119Z","updated":"2018-01-24T22:01:23.119Z","metadata":null,"synonyms":["AS400","Laptop","Mac","Mainframe","PC"]}],"created":"2018-01-24T22:01:23.119Z","updated":"2018-01-24T22:01:23.119Z","metadata":null,"description":null},{"entity":"sys-time","values":[],"created":"2018-01-24T22:01:23.119Z","updated":"2018-01-24T22:01:23.119Z","metadata":null,"description":null},{"entity":"severity","values":[{"type":"synonyms","value":"1","created":"2018-01-24T22:33:57.880Z","updated":"2018-01-25T03:33:22.271Z","metadata":null,"synonyms":["1","high","h"]},{"type":"synonyms","value":"2","created":"2018-01-24T22:34:13.738Z","updated":"2018-01-25T03:33:28.794Z","metadata":null,"synonyms":["2","medium","m"]},{"type":"synonyms","value":"3","created":"2018-01-24T22:34:26.283Z","updated":"2018-01-25T03:33:34.352Z","metadata":null,"synonyms":["3","low","l"]}],"created":"2018-01-24T22:33:34.737Z","updated":"2018-01-25T03:33:34.352Z","metadata":null,"description":null},{"entity":"Software","values":[{"type":"synonyms","value":"Mail Server","created":"2018-01-24T22:01:23.119Z","updated":"2018-01-24T22:01:23.119Z","metadata":null,"synonyms":["Lotus Notes","MS Exchange"]},{"type":"synonyms","value":"Application server","created":"2018-01-24T22:01:23.119Z","updated":"2018-01-24T22:01:23.119Z","metadata":null,"synonyms":["WebSphere","WebLogic","TomCat"]},{"type":"synonyms","value":"Database","created":"2018-01-24T22:01:23.119Z","updated":"2018-01-24T22:01:23.119Z","metadata":null,"synonyms":["DB2","Oracle","Infosys","Cla","NoSQL","MongoDB"]}],"created":"2018-01-24T22:01:23.119Z","updated":"2018-01-24T22:01:23.119Z","metadata":null,"description":null},{"entity":"sys-date","values":[],"created":"2018-01-24T22:01:23.119Z","updated":"2018-01-24T22:01:23.119Z","metadata":null,"description":null},{"entity":"description","values":[],"created":"2018-01-24T22:29:10.912Z","updated":"2018-01-24T22:29:10.912Z","metadata":null,"description":null},{"entity":"Network","values":[{"type":"synonyms","value":"network","created":"2018-01-24T22:01:23.119Z","updated":"2018-01-24T22:01:23.119Z","metadata":null,"synonyms":["Network"]},{"type":"synonyms","value":"firewall","created":"2018-01-24T22:01:23.119Z","updated":"2018-01-24T22:01:23.119Z","metadata":null,"synonyms":["Firewall"]},{"type":"synonyms","value":"wireless","created":"2018-01-24T22:01:23.119Z","updated":"2018-01-24T22:01:23.119Z","metadata":null,"synonyms":["Wireless"]},{"type":"synonyms","value":"swtich","created":"2018-01-24T22:01:23.119Z","updated":"2018-01-24T22:01:23.119Z","metadata":null,"synonyms":["Swtich"]},{"type":"synonyms","value":"router","created":"2018-01-24T22:01:23.119Z","updated":"2018-01-24T22:01:23.119Z","metadata":null,"synonyms":["Router"]}],"created":"2018-01-24T22:01:23.119Z","updated":"2018-01-24T22:01:23.119Z","metadata":null,"description":null}],"language":"en","metadata":{"api_version":{"major_version":"v1","minor_version":"2017-05-26"}},"description":"Simple IT help desk","dialog_nodes":[{"type":"slot","title":null,"output":{},"parent":"node_1_1516850017677","context":null,"created":"2018-01-25T03:24:05.049Z","updated":"2018-01-26T20:51:38.065Z","metadata":{},"variable":"$severity","next_step":null,"conditions":null,"description":null,"dialog_node":"slot_6_1516850647245","previous_sibling":"node_13_1516852865520"},{"type":"standard","title":"to be opened","output":{"text":{"values":["Thank you for contacting IT help desk. A new ticket is opened."],"selection_policy":"sequential"}},"parent":"node_1_1516850017677","context":null,"created":"2018-01-25T04:01:03.349Z","updated":"2018-01-27T06:20:36.794Z","metadata":{},"next_step":{"behavior":"jump_to","selector":"user_input","dialog_node":"Welcome"},"conditions":"$newticket","description":null,"dialog_node":"node_13_1516852865520","previous_sibling":null},{"type":"event_handler","title":null,"output":{"text":"Do you want to create a new ticket?"},"parent":"slot_12_1516999972119","context":null,"created":"2018-01-26T20:52:48.338Z","updated":"2018-01-26T20:52:48.338Z","metadata":{},"next_step":null,"conditions":null,"event_name":"focus","description":null,"dialog_node":"handler_14_1516999972119","previous_sibling":"handler_13_1516999972119"},{"type":"event_handler","title":null,"output":{},"parent":"slot_12_1516999972119","context":{"newticket":"@new_ticket"},"created":"2018-01-26T20:52:48.338Z","updated":"2018-01-26T20:52:48.338Z","metadata":{},"next_step":null,"conditions":"@new_ticket","event_name":"input","description":null,"dialog_node":"handler_13_1516999972119","previous_sibling":null},{"type":"slot","title":null,"output":{},"parent":"node_10_1516999972115","context":null,"created":"2018-01-26T20:52:48.338Z","updated":"2018-01-26T20:52:48.338Z","metadata":{},"variable":"$newticket","next_step":null,"conditions":null,"description":null,"dialog_node":"slot_12_1516999972119","previous_sibling":"node_1_1516850017677"},{"type":"frame","title":"open a new ticket 2","output":{},"parent":"node_10_1516999972115","context":null,"created":"2018-01-25T03:13:35.661Z","updated":"2018-01-26T21:30:18.997Z","metadata":{"fallback":"leave"},"next_step":{"behavior":"jump_to","selector":"condition","dialog_node":"node_13_1516852865520"},"conditions":"@new_ticket:true","description":null,"dialog_node":"node_1_1516850017677","digress_out":"allow_all","previous_sibling":"node_18_1517000905140","digress_out_slots":"not_allowed"},{"type":"standard","title":"no ticket","output":{"text":{"values":["Thank you for contacting help desk. No ticket to be opened."],"selection_policy":"sequential"}},"parent":"node_10_1516999972115","context":null,"created":"2018-01-26T21:08:21.301Z","updated":"2018-01-26T21:30:00.568Z","metadata":{},"next_step":{"behavior":"jump_to","selector":"body","dialog_node":"Welcome"},"conditions":"@new_ticket:no","description":null,"dialog_node":"node_18_1517000905140","previous_sibling":"node_20_1517017786483"},{"type":"standard","title":null,"output":{},"parent":"node_10_1516999972115","context":null,"created":"2018-01-27T01:49:42.787Z","updated":"2018-01-27T01:49:50.713Z","metadata":{},"next_step":null,"conditions":"false","description":null,"dialog_node":"node_20_1517017786483","previous_sibling":null},{"type":"frame","title":"open a new ticket 1","output":{},"parent":"node_5_1516850287208","context":null,"created":"2018-01-26T20:52:48.338Z","updated":"2018-01-27T06:03:52.719Z","metadata":{"fallback":"leave"},"next_step":{"behavior":"jump_to","selector":"condition","dialog_node":"node_20_1517017786483"},"conditions":"","description":null,"dialog_node":"node_10_1516999972115","digress_out":"allow_all","previous_sibling":null,"digress_out_slots":"not_allowed"},{"type":"standard","title":null,"output":{"text":{"values":[""],"selection_policy":"sequential"}},"parent":"node_1_1516831815177","context":null,"created":"2018-01-24T22:20:12.799Z","updated":"2018-01-25T03:28:21.398Z","metadata":{},"next_step":{"behavior":"jump_to","selector":"body","dialog_node":"node_5_1516850287208"},"conditions":"@Software != ''","description":null,"dialog_node":"node_6_1516832414895","previous_sibling":"node_4_1516832287824"},{"type":"standard","title":null,"output":{"text":{"values":["Please power off wireless router in the conference room, waiting one minute and power it on"],"selection_policy":"sequential"}},"parent":"node_1_1516831815177","context":null,"created":"2018-01-24T22:18:05.596Z","updated":"2018-01-25T03:39:53.505Z","metadata":{},"next_step":null,"conditions":"@Network:wireless","description":null,"dialog_node":"node_4_1516832287824","previous_sibling":"node_3_1516832266395"},{"type":"standard","title":null,"output":{"text":{"values":["Please reboot your machine"],"selection_policy":"sequential"}},"parent":"node_1_1516831815177","context":null,"created":"2018-01-24T22:17:44.252Z","updated":"2018-01-25T03:07:26.889Z","metadata":{},"next_step":null,"conditions":"@Hardware:Computer","description":null,"dialog_node":"node_3_1516832266395","previous_sibling":null},{"type":"event_handler","title":null,"output":{"text":"What severity do you want for your new ticket (high, medium, low)?"},"parent":"slot_6_1516850647245","context":null,"created":"2018-01-25T03:24:05.521Z","updated":"2018-01-26T20:32:36.750Z","metadata":{},"next_step":null,"conditions":null,"event_name":"focus","description":null,"dialog_node":"handler_8_1516850647245","previous_sibling":"handler_7_1516850647245"},{"type":"event_handler","title":null,"output":{},"parent":"slot_6_1516850647245","context":{"severity":"@severity"},"created":"2018-01-25T03:24:05.283Z","updated":"2018-01-26T20:51:38.310Z","metadata":{},"next_step":null,"conditions":"@severity","event_name":"input","description":null,"dialog_node":"handler_7_1516850647245","previous_sibling":null},{"type":"standard","title":null,"output":{},"parent":null,"context":null,"created":"2018-01-24T22:37:53.275Z","updated":"2018-01-24T22:39:08.340Z","metadata":{},"next_step":{"behavior":"jump_to","selector":"body","dialog_node":"Welcome"},"conditions":"#greetings","description":null,"dialog_node":"node_19_1516833475477","previous_sibling":"Welcome"},{"type":"standard","title":"Anything else","output":{"text":{"values":["I didn't understand. You can try rephrasing.","Can you reword your statement? I'm not understanding.","I didn't get your meaning."],"selection_policy":"sequential"}},"parent":null,"context":null,"created":"2018-01-24T22:04:22.181Z","updated":"2018-01-25T03:17:38.000Z","metadata":{},"next_step":null,"conditions":"anything_else","description":null,"dialog_node":"Anything else","previous_sibling":"node_5_1516850287208"},{"type":"standard","title":"Bye","output":{"text":{"values":["Thank you for contacting IT help desk. Have a good day!"],"selection_policy":"sequential"}},"parent":null,"context":null,"created":"2018-01-24T22:39:50.191Z","updated":"2018-01-25T03:18:59.171Z","metadata":{},"next_step":{"behavior":"jump_to","selector":"user_input","dialog_node":"Welcome"},"conditions":"#goodbyes","digress_in":"does_not_return","description":null,"dialog_node":"node_20_1516833592391","previous_sibling":"node_1_1516831815177"},{"type":"standard","title":"it_helpdesk","output":{},"parent":null,"context":null,"created":"2018-01-24T22:10:13.145Z","updated":"2018-01-25T03:07:51.192Z","metadata":{},"next_step":{"behavior":"jump_to","selector":"condition","dialog_node":"node_3_1516832266395"},"conditions":"#IT_helpdesk","description":null,"dialog_node":"node_1_1516831815177","previous_sibling":"node_19_1516833475477"},{"type":"standard","title":"Ticketing","output":{"text":{"values":["No quick resolution is available."],"selection_policy":"sequential"}},"parent":null,"context":null,"created":"2018-01-25T03:18:05.405Z","updated":"2018-01-26T20:58:09.096Z","metadata":{},"next_step":{"behavior":"jump_to","selector":"body","dialog_node":"node_10_1516999972115"},"conditions":null,"description":null,"dialog_node":"node_5_1516850287208","previous_sibling":"node_20_1516833592391"},{"type":"standard","title":"Welcome","output":{"text":{"values":["Hello. How can I help you?"],"selection_policy":"sequential"}},"parent":null,"context":null,"created":"2018-01-24T22:04:22.181Z","updated":"2018-01-24T22:04:22.181Z","metadata":{},"next_step":null,"conditions":"welcome","description":null,"dialog_node":"Welcome","previous_sibling":null}],"workspace_id":"8e9097c4-59a1-4b50-a629-1e224e7e2de1","counterexamples":[{"text":"aho","created":"2018-01-24T22:01:23.119Z","updated":"2018-01-24T22:01:23.119Z"},{"text":"asdasdasda","created":"2018-01-24T22:01:23.119Z","updated":"2018-01-24T22:01:23.119Z"},{"text":"asdasidjiwe","created":"2018-01-24T22:01:23.119Z","updated":"2018-01-24T22:01:23.119Z"},{"text":"cats are my favorite animal","created":"2018-01-24T22:01:23.119Z","updated":"2018-01-24T22:01:23.119Z"},{"text":"when will it be funny","created":"2018-01-24T22:01:23.119Z","updated":"2018-01-24T22:01:23.119Z"},{"text":"which color is best for wedding","created":"2018-01-24T22:01:23.119Z","updated":"2018-01-24T22:01:23.119Z"}],"learning_opt_out":false}